mpylab/LICENSE
mpylab/__init__.py
mpylab/device/Meta_ui.py
mpylab/device/__init__.py
mpylab/device/amp_ar_25s1g4.py
mpylab/device/amp_blma_1018_100.py
mpylab/device/amp_blwa_0810_100.py
mpylab/device/amp_cba_1g_030d.py
mpylab/device/amp_ifi_smx25.py
mpylab/device/amplifier.py
mpylab/device/device.py
mpylab/device/driver.py
mpylab/device/driver_new.py
mpylab/device/fieldprobe.py
mpylab/device/fieldprobe_ui.py
mpylab/device/mc_teseq_stirrer.py
mpylab/device/motorcontroller.py
mpylab/device/mpy_exceptions.py
mpylab/device/networkanalyzer.py
mpylab/device/networkanalyzer_ui.py
mpylab/device/nport.py
mpylab/device/nw_rs_zlv.py
mpylab/device/pm_gt_8540c.py
mpylab/device/pm_lumiloop_lspm.py
mpylab/device/pm_rs_nrp.py
mpylab/device/pm_rxatt.py
mpylab/device/pmini.ini
mpylab/device/powermeter.py
mpylab/device/powermeter2c.py
mpylab/device/powermeter_ui.py
mpylab/device/prb_ar_fm7004.py
mpylab/device/prb_lumiloop_lsprobe.py
mpylab/device/prb_pmm_ep601.py
mpylab/device/r_types.py
mpylab/device/sg_gt_12000a.py
mpylab/device/sg_rs_smb100a.py
mpylab/device/sg_rs_smc100a.py
mpylab/device/sg_rs_smf100a.py
mpylab/device/sg_rs_smr.py
mpylab/device/sg_rs_swm.py
mpylab/device/signalgenerator.py
mpylab/device/signalgenerator_ui.py
mpylab/device/sp_rs_zlv-6.py
mpylab/device/spectrumanalyzer.py
mpylab/device/spectrumanalyzer_ui.py
mpylab/device/switch.py
mpylab/device/tools.py
mpylab/device/validators.py
mpylab/env/Measure.py
mpylab/env/__init__.py
mpylab/env/custom.py
mpylab/env/msc/ImmunityThreshold.py
mpylab/env/msc/MSC.py
mpylab/env/msc/__init__.py
mpylab/env/tem/TEMCell.py
mpylab/env/tem/__init__.py
mpylab/env/univers/AmplifierTest.py
mpylab/env/univers/__init__.py
mpylab/tools/Configuration.py
mpylab/tools/PControler.py
mpylab/tools/__init__.py
mpylab/tools/aunits.py
mpylab/tools/calling.py
mpylab/tools/correlation.py
mpylab/tools/dataparser.py
mpylab/tools/directivity.py
mpylab/tools/distributions.py
mpylab/tools/dot.g
mpylab/tools/dot.py
mpylab/tools/interpol.py
mpylab-0.9.5.dist-info/licenses/LICENSE
mpylab-0.9.5.dist-info/WHEEL
mpylab-0.9.5.dist-info/METADATA
mpylab-0.9.5.dist-info/RECORD
