Metadata-Version: 2.4
Name: mpylab
Version: 0.9.5
Summary: A framework to simplify development of measurement 'scripts' for measurements in laboratories over e.g pyvisa.
Keywords: pyvisa,gpib,measurements,laboratory
Author: Hans Georg Krauthäuser, Christian Albrecht, Stephan, Oscar Rivera, Mathias Magdowski, Sophie Rautschek, Frank Schröder, Luzia Tesar, Konstantin Pasche, Thomas Reidemeister
Author-email: Hans Georg Krauthäuser <hgk@ieee.org>
License-Expression: GPL-3.0-or-later
License-File: LICENSE
Classifier: Development Status :: 4 - Beta
Classifier: Intended Audience :: Developers
Classifier: Intended Audience :: Education
Classifier: Intended Audience :: Science/Research
Classifier: License :: OSI Approved :: GNU General Public License v3 or later (GPLv3+)
Classifier: Topic :: Scientific/Engineering
Classifier: Programming Language :: Python :: 3
Classifier: Programming Language :: Python :: 3.8
Classifier: Programming Language :: Python :: 3.9
Classifier: Programming Language :: Python :: 3.10
Classifier: Programming Language :: Python :: 3.11
Classifier: Programming Language :: Python :: 3.12
Classifier: Programming Language :: Python :: 3.13
Requires-Dist: bidict>=0.23.1
Requires-Dist: gpib-ctypes>=0.3.0
Requires-Dist: levenshtein>=0.27.1
Requires-Dist: matplotlib>=3.7.5
Requires-Dist: msvcrt ; sys_platform == 'win32'
Requires-Dist: numpy>=1.24.4
Requires-Dist: pathvalidate>=3.3.1
Requires-Dist: ply>=3.11
Requires-Dist: pydot>=4.0.1
Requires-Dist: pyparsing>=3.1.4
Requires-Dist: pyserial>=3.5
Requires-Dist: pyusb>=1.2.1
Requires-Dist: pyvisa>=1.14.1
Requires-Dist: pyvisa-py>=0.7.2
Requires-Dist: scipy>=1.10.1
Requires-Dist: scuq>=0.9
Requires-Dist: simpleeval>=0.9.13
Requires-Dist: pyside6 ; extra == 'gui'
Maintainer: Hans Georg Krauthäuser
Maintainer-email: Hans Georg Krauthäuser <hgk@ieee.org>
Requires-Python: >=3.8
Project-URL: Repository, https://github.com/hgkdd/Mpy
Provides-Extra: gui
